src/__init__.py
src/aws/__init__.py
src/aws/client.py
src/aws/credentials.py
src/aws/rate_limiter.py
src/cli/__init__.py
src/cli/config.py
src/cli/deletion_progress.py
src/cli/main.py
src/cloudtrail/__init__.py
src/cloudtrail/query.py
src/config_service/__init__.py
src/config_service/collector.py
src/config_service/detector.py
src/config_service/resource_type_mapping.py
src/copilot/__init__.py
src/copilot/installer.py
src/copilot/models.py
src/copilot/version.py
src/copilot/templates/__init__.py
src/copilot/templates/copilot-instructions.md
src/copilot/templates/instructions/__init__.py
src/copilot/templates/instructions/terraform.instructions.md
src/copilot/templates/prompts/generate-cdk-python.prompt.md
src/copilot/templates/prompts/generate-cdk-typescript.prompt.md
src/copilot/templates/prompts/generate-terraform-layer.prompt.md
src/copilot/templates/prompts/generate-terraform.prompt.md
src/copilot/templates/prompts/plan-iac.prompt.md
src/cost/__init__.py
src/cost/analyzer.py
src/cost/explorer.py
src/cost/reporter.py
src/delta/__init__.py
src/delta/calculator.py
src/delta/differ.py
src/delta/formatters.py
src/delta/models.py
src/delta/reporter.py
src/generate/__init__.py
src/generate/agent.py
src/generate/layers.py
src/generate/state.py
src/generate/terraform_generator.py
src/generate/nodes/__init__.py
src/generate/nodes/build_resource_map.py
src/generate/nodes/categorize_layers.py
src/generate/nodes/extract_lambda.py
src/generate/nodes/generate_layer.py
src/generate/nodes/parse_inventory.py
src/generate/nodes/validate_terraform.py
src/generate/prompts/__init__.py
src/generate/prompts/terraform.py
src/generate/property_maps/__init__.py
src/generate/property_maps/apigateway.py
src/generate/property_maps/backup.py
src/generate/property_maps/cloudformation.py
src/generate/property_maps/cloudwatch.py
src/generate/property_maps/codebuild.py
src/generate/property_maps/codepipeline.py
src/generate/property_maps/dynamodb.py
src/generate/property_maps/ec2.py
aws_inventory_manager-0.31.1.dist-info/LICENSE
aws_inventory_manager-0.31.1.dist-info/METADATA
aws_inventory_manager-0.31.1.dist-info/WHEEL
aws_inventory_manager-0.31.1.dist-info/entry_points.txt
aws_inventory_manager-0.31.1.dist-info/top_level.txt
aws_inventory_manager-0.31.1.dist-info/RECORD
