Metadata-Version: 2.2
Name: aws-inventory-manager
Version: 0.31.1
Summary: AWS Resource Inventory Management & Delta Tracking CLI tool
Author-email: Troy Larson <troy@calvinware.com>
License: MIT
Project-URL: Homepage, https://github.com/troylar/aws-inventory-manager
Project-URL: Documentation, https://github.com/troylar/aws-inventory-manager#readme
Project-URL: Repository, https://github.com/troylar/aws-inventory-manager
Project-URL: Issues, https://github.com/troylar/aws-inventory-manager/issues
Keywords: aws,cloud,infrastructure,snapshot,audit,cost-tracking,inventory
Classifier: Development Status :: 5 - Production/Stable
Classifier: Intended Audience :: Developers
Classifier: Intended Audience :: System Administrators
Classifier: Programming Language :: Python :: 3
Classifier: Programming Language :: Python :: 3.11
Classifier: Programming Language :: Python :: 3.12
Classifier: Programming Language :: Python :: 3.13
Classifier: Programming Language :: Python :: 3.14
Classifier: Topic :: System :: Systems Administration
Classifier: Topic :: Utilities
Requires-Python: >=3.11
License-File: LICENSE
Requires-Dist: boto3>=1.28.0
Requires-Dist: typer>=0.9.0
Requires-Dist: rich>=13.0.0
Requires-Dist: pyyaml>=6.0
Requires-Dist: python-dateutil>=2.8.0
Requires-Dist: requests>=2.28.0
Provides-Extra: dev
Requires-Dist: pytest>=7.0.0; extra == "dev"
Requires-Dist: pytest-cov>=4.0.0; extra == "dev"
Requires-Dist: pytest-mock>=3.12.0; extra == "dev"
Requires-Dist: ruff>=0.9.0; extra == "dev"
Requires-Dist: mypy>=1.0.0; extra == "dev"
Requires-Dist: types-PyYAML>=6.0.0; extra == "dev"
Requires-Dist: invoke>=2.0.0; extra == "dev"
Provides-Extra: web
Requires-Dist: fastapi>=0.109.0; extra == "web"
Requires-Dist: uvicorn[standard]>=0.27.0; extra == "web"
Requires-Dist: jinja2>=3.1.0; extra == "web"
Requires-Dist: python-multipart>=0.0.6; extra == "web"
Provides-Extra: generate
Requires-Dist: langgraph>=0.2.0; extra == "generate"
